LICENSE.txt
MANIFEST.in
README.txt
setup.py
pcart_cart/__init__.py
pcart_cart/admin.py
pcart_cart/apps.py
pcart_cart/cms_apps.py
pcart_cart/forms.py
pcart_cart/models.py
pcart_cart/payment.py
pcart_cart/shipping.py
pcart_cart/urls.py
pcart_cart/utils.py
pcart_cart/views.py
pcart_cart.egg-info/PKG-INFO
pcart_cart.egg-info/SOURCES.txt
pcart_cart.egg-info/dependency_links.txt
pcart_cart.egg-info/not-zip-safe
pcart_cart.egg-info/requires.txt
pcart_cart.egg-info/top_level.txt
pcart_cart/locale/ru/LC_MESSAGES/django.mo
pcart_cart/locale/ru/LC_MESSAGES/django.po
pcart_cart/locale/uk/LC_MESSAGES/django.mo
pcart_cart/locale/uk/LC_MESSAGES/django.po
pcart_cart/migrations/0001_initial.py
pcart_cart/migrations/0002_order_ordernumberformat.py
pcart_cart/migrations/0003_auto_20170212_1345.py
pcart_cart/migrations/0004_auto_20170222_1918.py
pcart_cart/migrations/0005_orderstatus.py
pcart_cart/migrations/0006_order_status.py
pcart_cart/migrations/0007_order_export_status.py
pcart_cart/migrations/__init__.py
pcart_cart/templates/admin/cart/cart_preview.html
pcart_cart/templates/admin/cart/order_preview.html
pcart_cart/templates/admin/cart/withparamsshipping_preview.html
pcart_cart/templates/admin/cart/withparamsshipping_preview.txt